tea2adt-0.5.data/data/README.md
tea2adt-0.5.data/data/tea2adt/gpg.src
tea2adt-0.5.data/data/tea2adt/gpgappend.src
tea2adt-0.5.data/data/tea2adt/install_dependencies.sh
tea2adt-0.5.data/data/tea2adt/killtea2adt.sh
tea2adt-0.5.data/data/tea2adt/mmack.sh
tea2adt-0.5.data/data/tea2adt/mmdata.sh
tea2adt-0.5.data/data/tea2adt/mmrxnopwd.sh
tea2adt-0.5.data/data/tea2adt/mmsessionout.sh
tea2adt-0.5.data/data/tea2adt/mmtx.sh
tea2adt-0.5.data/data/tea2adt/mmtxfile.sh
tea2adt-0.5.data/data/tea2adt/mute_mic.sh
tea2adt-0.5.data/data/tea2adt/restore_audio_settings.sh
tea2adt-0.5.data/data/tea2adt/rx.src
tea2adt-0.5.data/data/tea2adt/set_interfaces.sh
tea2adt-0.5.data/data/tea2adt/stt.sh
tea2adt-0.5.data/data/tea2adt/tea2adt
tea2adt-0.5.data/data/tea2adt/tea2adt.png
tea2adt-0.5.data/data/tea2adt/tts.sh
tea2adt-0.5.data/data/tea2adt/tx.src
tea2adt-0.5.data/data/tea2adt/unmute_mic.sh
tea2adt-0.5.data/data/tea2adt/version
tea2adt-0.5.data/data/tea2adt/cfg/armor
tea2adt-0.5.data/data/tea2adt/cfg/baud
tea2adt-0.5.data/data/tea2adt/cfg/cipher_algo
tea2adt-0.5.data/data/tea2adt/cfg/confidence
tea2adt-0.5.data/data/tea2adt/cfg/end_msg
tea2adt-0.5.data/data/tea2adt/cfg/half_duplex
tea2adt-0.5.data/data/tea2adt/cfg/install_dependencies
tea2adt-0.5.data/data/tea2adt/cfg/interface_index_minimodem_in
tea2adt-0.5.data/data/tea2adt/cfg/interface_index_minimodem_out
tea2adt-0.5.data/data/tea2adt/cfg/interface_index_stt_in
tea2adt-0.5.data/data/tea2adt/cfg/interface_index_tts_out
tea2adt-0.5.data/data/tea2adt/cfg/keepalive_time_sec
tea2adt-0.5.data/data/tea2adt/cfg/limit
tea2adt-0.5.data/data/tea2adt/cfg/llm_cmd
tea2adt-0.5.data/data/tea2adt/cfg/log_to_file
tea2adt-0.5.data/data/tea2adt/cfg/logging_level
tea2adt-0.5.data/data/tea2adt/cfg/max_retransmissions
tea2adt-0.5.data/data/tea2adt/cfg/need_ack
tea2adt-0.5.data/data/tea2adt/cfg/preamble
tea2adt-0.5.data/data/tea2adt/cfg/probe_msg
tea2adt-0.5.data/data/tea2adt/cfg/probe_sleep
tea2adt-0.5.data/data/tea2adt/cfg/redundant_transmissions
tea2adt-0.5.dist-info/LICENSE
tea2adt-0.5.dist-info/METADATA
tea2adt-0.5.dist-info/WHEEL
tea2adt-0.5.dist-info/entry_points.txt
tea2adt-0.5.dist-info/top_level.txt
tea2adt-0.5.dist-info/RECORD
